chroma_mcp/__init__.py
chroma_mcp/server.py
iflow_mcp_chroma_core_chroma_mcp-0.2.6.dist-info/METADATA
iflow_mcp_chroma_core_chroma_mcp-0.2.6.dist-info/WHEEL
iflow_mcp_chroma_core_chroma_mcp-0.2.6.dist-info/entry_points.txt
iflow_mcp_chroma_core_chroma_mcp-0.2.6.dist-info/licenses/LICENSE
iflow_mcp_chroma_core_chroma_mcp-0.2.6.dist-info/RECORD
