Metadata-Version: 2.4
Name: iflow-mcp_chroma-core_chroma-mcp
Version: 0.2.6
Summary: Chroma MCP Server - Vector Database Integration for LLM Applications
Project-URL: Homepage, https://github.com/chroma-core/chroma-mcp
Project-URL: Documentation, https://github.com/chroma-core/chroma-mcp#readme
Project-URL: Issues, https://github.com/chroma-core/chroma-mcp/issues
License-Expression: Apache-2.0
License-File: LICENSE
Keywords: chroma,embeddings,llm,mcp,vector-database
Classifier: Development Status :: 4 - Beta
Classifier: Intended Audience :: Developers
Classifier: License :: OSI Approved :: Apache Software License
Classifier: Programming Language :: Python :: 3
Classifier: Programming Language :: Python :: 3.10
Classifier: Topic :: Software Development :: Libraries :: Python Modules
Requires-Python: >=3.10
Requires-Dist: chromadb>=1.0.16
Requires-Dist: cohere>=5.14.2
Requires-Dist: httpx>=0.28.1
Requires-Dist: mcp[cli]==1.6.0
Requires-Dist: openai>=1.70.0
Requires-Dist: pillow>=11.1.0
Requires-Dist: python-dotenv>=0.19.0
Requires-Dist: typing-extensions>=4.13.1
Requires-Dist: voyageai>=0.3.2
Provides-Extra: sentence-transformers
Requires-Dist: sentence-transformers>=4.1.0; extra == 'sentence-transformers'
Provides-Extra: test
Requires-Dist: pytest-asyncio>=0.26.0; extra == 'test'
Requires-Dist: pytest-cov>=4.1.0; extra == 'test'
Requires-Dist: pytest>=8.3.5; extra == 'test'
